MANIFEST.in
README.md
requirements.txt
setup.py
google/__init__.py
google/core.py
google.py.egg-info/PKG-INFO
google.py.egg-info/SOURCES.txt
google.py.egg-info/dependency_links.txt
google.py.egg-info/entry_points.txt
google.py.egg-info/requires.txt
google.py.egg-info/top_level.txt
google/data/ips.json