Metadata-Version: 1.1
Name: google.py
Version: 0.1.1
Summary: Search available fast google ip for blocked users
Home-page: https://github.com/Jayin/core.py
Author: Jayin Ton
Author-email: tonjayin@gmail.com
License: BSD
Download-URL: https://github.com/Jayin/google.py
Platform: UNKNOWN
Classifier: Development Status :: 5 - Production/Stable
Classifier: Programming Language :: Python
Classifier: Programming Language :: Python :: 2.7
Classifier: Environment :: Console
Classifier: Intended Audience :: Developers
Classifier: License :: OSI Approved :: BSD License
Classifier: Topic :: Utilities
